{
  "users": [
    {
      "id": "taras.frbslist@gmail.com",
      "firstName": "Joe",
      "lastName": "Tribiani",
      "password": "1234",
      "notes": [
        {
          "id": 1660739251553,
          "text": "1",
          "subNotes": [
            {
              "id": 1660739279049,
              "text": "11",
              "subNotes": []
            },
            {
              "id": 1660739282664,
              "text": "12",
              "subNotes": []
            }
          ]
        },
        {
          "id": 1660739253495,
          "text": "2",
          "subNotes": []
        },
        {
          "id": 1660739257392,
          "text": "3",
          "subNotes": []
        }
      ]
    },
    {
      "id": "t@in.ua",
      "firstName": "sfsfe",
      "lastName": "fsefsfe",
      "password": "1234",
      "notes": [
        {
          "id": 1660663948258,
          "text": "1",
          "subNotes": []
        },
        {
          "id": 1660663950642,
          "text": "2",
          "subNotes": []
        },
        {
          "id": 1660664022760,
          "text": "3",
          "subNotes": []
        }
      ]
    }
  ]
}